cv_videowriter/__init__.py
cv_videowriter/videowriter.py
cv_videowriter-0.1.0.dist-info/METADATA
cv_videowriter-0.1.0.dist-info/WHEEL
cv_videowriter-0.1.0.dist-info/top_level.txt
cv_videowriter-0.1.0.dist-info/RECORD
