Metadata-Version: 2.1
Name: cv_videowriter
Version: 0.1.0
Summary: Wrapper around OpenCV VideoWriter with some extra features
Author: Ibai Gorordo
License: MIT
Project-URL: Homepage, https://github.com/ibaiGorordo/cv_videowriter
Requires-Dist: opencv-python
